pynihongo/__init__.py
pynihongo/kana.py
pynihongo/method.py
PyNihongo-0.0.1.dev5.dist-info/LICENSE
PyNihongo-0.0.1.dev5.dist-info/METADATA
PyNihongo-0.0.1.dev5.dist-info/WHEEL
PyNihongo-0.0.1.dev5.dist-info/top_level.txt
PyNihongo-0.0.1.dev5.dist-info/RECORD
