Metadata-Version: 2.1
Name: PyNihongo
Version: 0.0.1.dev5
Summary: A Python package about japanese.
Author: Koushoken
Author-email: kskjcx-dev@yahoo.co.jp
License-File: LICENSE
